ipp_ds/__init__.py
ipp_ds/data_cleaning/__init__.py
ipp_ds/data_cleaning/dates_holidays.py
ipp_ds/data_cleaning/feature_engineering.py
ipp_ds/data_cleaning/file_reading.py
ipp_ds/data_cleaning/parallelism.py
ipp_ds/data_cleaning/path.py
ipp_ds/data_cleaning/text_type.py
ipp_ds/data_cleaning/utils.py
ipp_ds/io/__init__.py
ipp_ds/io/io.py
ipp_ds/io/io_utils.py
ipp_ds/io/keyvault.py
ipp_ds/ipp_ds.egg-info/PKG-INFO
ipp_ds/ipp_ds.egg-info/SOURCES.txt
ipp_ds/ipp_ds.egg-info/dependency_links.txt
ipp_ds/ipp_ds.egg-info/not-zip-safe
ipp_ds/ipp_ds.egg-info/requires.txt
ipp_ds/ipp_ds.egg-info/top_level.txt
ipp_ds/ml/__init__.py
ipp_ds/ml/time_series/__init__.py
ipp_ds/variables/__init__.py
ipp_ds/variables/dates.py
ipp_ds/variables/geo.py
ipp_ds/visualization/__init__.py
ipp_ds-0.5.2.1.dist-info/METADATA
ipp_ds-0.5.2.1.dist-info/WHEEL
ipp_ds-0.5.2.1.dist-info/top_level.txt
ipp_ds-0.5.2.1.dist-info/RECORD
