Metadata-Version: 2.1
Name: ipp-ds
Version: 0.5.2.1
Summary: Biblioteca da área de Ciencia de Dados da Ipiranga Produtos de Petroleo
Author: Ciencia de Dados
Author-email: gabriel.d@ipiranga.ipiranga
License: MIT
Platform: UNKNOWN
Requires-Python: >=3.7.1
Requires-Dist: azure-identity
Requires-Dist: azure-keyvault
Requires-Dist: azure-keyvault-secrets
Requires-Dist: azure-storage-file-datalake
Requires-Dist: holidays
Requires-Dist: importlib-metadata
Requires-Dist: joblib
Requires-Dist: openpyxl
Requires-Dist: numpy
Requires-Dist: pandas
Requires-Dist: pyarrow
Requires-Dist: pyexcelerate
Requires-Dist: python-dotenv
Requires-Dist: python-pptx
Requires-Dist: thinkcell
Requires-Dist: setuptools
Requires-Dist: wheel
Requires-Dist: xlrd
